{
    "topic": "Grade 5 - English - Grammar",
    "short_answer": [
        {
            "question": "According to the text, what are two things trees do to help prevent floods?",
            "answer": "Trees slow down rainwater and help the soil soak up the water."
        },
        {
            "question": "The text mentions that a flood can cause a loss of crops. What important supply does this affect?",
            "answer": "A loss of crops affects the food supply."
        }
    ],
    "mcq": [
        {
            "question": "Based on the context, what happens when there are no trees to slow down rainwater?",
            "options": {
                "a": "The soil soaks up more water.",
                "b": "The river becomes cleaner.",
                "c": "Water runs off the land faster and causes flooding.",
                "d": "There is more water for everyone during the summer."
            },
            "answer": "c"
        },
        {
            "question": "The Ganges river dolphin is blind. How does it find its way in the water?",
            "options": {
                "a": "By using its sense of smell",
                "b": "By using sound",
                "c": "By following the river current",
                "d": "By seeing light and shadows"
            },
            "answer": "b"
        }
    ],
    "fill_in_the_blanks": [
        {
            "question": "The Ganges river dolphin is described as India’s national __________ animal.",
            "answer": "aquatic"
        },
        {
            "question": "To save water, you can reuse the clean water from washing fruits or vegetables to water the ________.",
            "answer": "plants"
        }
    ]
}